setup.cfg
setup.py
plat/__init__.py
plat/canvas_layout.py
plat/fuel_helper.py
plat/grid_layout.py
plat/interpolate.py
plat/sampling.py
plat/utils.py
plat/zoo.py
plat.egg-info/PKG-INFO
plat.egg-info/SOURCES.txt
plat.egg-info/dependency_links.txt
plat.egg-info/entry_points.txt
plat.egg-info/requires.txt
plat.egg-info/top_level.txt
plat/bin/__init__.py
plat/bin/atvec.py
plat/bin/download.py
plat/bin/facegrid.py
plat/bin/imgs2hdf5.py
plat/bin/plat-canvas.py
plat/bin/platcmd.py
plat/bin/sample.py
plat/interface/__init__.py
plat/interface/ali.py
plat/interface/example.py
plat/interface/ian.py
plat/interface/igan.py
plat/training/__init__.py
plat/training/samplecheckpoint.py