Metadata-Version: 1.1
Name: plat
Version: 0.2.0
Summary: Utilities for working with generative latent spaces
Home-page: https://github.com/dribnet/plat
Author: Tom White
Author-email: tom@sixdozen.com
License: MIT
Download-URL: https://github.com/dribnet/plat/archive/0.2.0.tar.gz
Platform: UNKNOWN
